my_own_package/__init__.py
bogdan_proiect_hello-0.2.0.dist-info/METADATA
bogdan_proiect_hello-0.2.0.dist-info/WHEEL
bogdan_proiect_hello-0.2.0.dist-info/top_level.txt
bogdan_proiect_hello-0.2.0.dist-info/RECORD
