Metadata-Version: 2.1
Name: bogdan-proiect-hello
Version: 0.2.0
Summary: says hello to owner
Author: Bogdan M.
Author-email: bogdan.m0792@yahoo.com
License: UNKNOWN
Platform: UNKNOWN
